sheetauto.py
sheetauto-0.0.1.dist-info/METADATA
sheetauto-0.0.1.dist-info/WHEEL
sheetauto-0.0.1.dist-info/top_level.txt
sheetauto-0.0.1.dist-info/RECORD
